MP4UploadDL/__init__.py
MP4UploadDL/__main__.py
MP4UploadDL/config.py
mp4uploaddl-1.0.2.dist-info/METADATA
mp4uploaddl-1.0.2.dist-info/WHEEL
mp4uploaddl-1.0.2.dist-info/entry_points.txt
mp4uploaddl-1.0.2.dist-info/top_level.txt
mp4uploaddl-1.0.2.dist-info/RECORD
