Metadata-Version: 2.4
Name: MP4UploadDL
Version: 1.0.2
Summary: A Python script to download videos from **MP4Upload** using the free download method without waiting.
Home-page: https://github.com/jo0x01/MP4UploadDL
Author: Jo0x01
License: MIT
Classifier: Development Status :: 4 - Beta
Classifier: Programming Language :: Python :: 3
Classifier: License :: OSI Approved :: MIT License
Classifier: Operating System :: OS Independent
Classifier: Topic :: Internet :: WWW/HTTP
Classifier: Topic :: Multimedia :: Video
Requires-Python: >=3.2
Requires-Dist: requests>=2.28.0
Requires-Dist: certifi>=2023.0.0
Requires-Dist: urllib3>=1.26.0
Dynamic: author
Dynamic: classifier
Dynamic: description
Dynamic: description-content-type
Dynamic: home-page
Dynamic: license
Dynamic: requires-dist
Dynamic: requires-python
Dynamic: summary
